nlp_xiaojiang/__init__.py
nlp_xiaojiang/AugmentText/__init__.py
nlp_xiaojiang/AugmentText/augment_eda/__init__.py
nlp_xiaojiang/AugmentText/augment_eda/enhance_eda.py
nlp_xiaojiang/AugmentText/augment_eda/enhance_word2vec.py
nlp_xiaojiang/AugmentText/augment_marko/__init__.py
nlp_xiaojiang/AugmentText/augment_marko/enhance_marko.py
nlp_xiaojiang/AugmentText/augment_seq2seq/__init__.py
nlp_xiaojiang/AugmentText/augment_seq2seq/code_seq2seq_char/__init__.py
nlp_xiaojiang/AugmentText/augment_seq2seq/code_seq2seq_char/extract_char_webank.py
nlp_xiaojiang/AugmentText/augment_seq2seq/code_seq2seq_char/predict_char_anti.py
nlp_xiaojiang/AugmentText/augment_seq2seq/code_seq2seq_char/train_char_anti.py
nlp_xiaojiang/AugmentText/augment_seq2seq/code_seq2seq_word/__init__.py
nlp_xiaojiang/AugmentText/augment_seq2seq/code_seq2seq_word/extract_webank.py
nlp_xiaojiang/AugmentText/augment_seq2seq/code_seq2seq_word/predict_word_anti.py
nlp_xiaojiang/AugmentText/augment_seq2seq/code_seq2seq_word/train_word_anti.py
nlp_xiaojiang/AugmentText/augment_syntax/__init__.py
nlp_xiaojiang/AugmentText/augment_syntax/augment_mainpart.py
nlp_xiaojiang/AugmentText/augment_translate/__init__.py
nlp_xiaojiang/AugmentText/augment_translate/translate_account/__init__.py
nlp_xiaojiang/AugmentText/augment_translate/translate_account/translate_tencent_secret.py
nlp_xiaojiang/AugmentText/augment_translate/translate_tools/__init__.py
nlp_xiaojiang/AugmentText/augment_translate/translate_tools/translate_translate.py
nlp_xiaojiang/AugmentText/augment_translate/translate_web/__init__.py
nlp_xiaojiang/AugmentText/augment_translate/translate_web/translate_google.py
nlp_xiaojiang/ChatBot/__init__.py
nlp_xiaojiang/ChatBot/chatbot_generate/__init__.py
nlp_xiaojiang/ChatBot/chatbot_generate/seq2seq/__init__.py
nlp_xiaojiang/ChatBot/chatbot_generate/seq2seq/code_seq2seq_char/__init__.py
nlp_xiaojiang/ChatBot/chatbot_generate/seq2seq/code_seq2seq_char/extract_char_cg.py
nlp_xiaojiang-0.0.1.dist-info/LICENSE
nlp_xiaojiang-0.0.1.dist-info/METADATA
nlp_xiaojiang-0.0.1.dist-info/WHEEL
nlp_xiaojiang-0.0.1.dist-info/top_level.txt
nlp_xiaojiang-0.0.1.dist-info/RECORD
