Metadata-Version: 2.1
Name: nlp-xiaojiang
Version: 0.0.1
Summary: nlp of augment、chatbot、classification and featureproject of chinese text
Home-page: https://github.com/yongzhuo/nlp_xiaojiang
Author: yongzhuo
Author-email: 1903865025@qq.com
License: MIT
Platform: UNKNOWN
Classifier: License :: OSI Approved :: MIT License
Classifier: Programming Language :: Python :: 3.4
Classifier: Programming Language :: Python :: 3.5
Classifier: Programming Language :: Python :: 3.6
Classifier: Programming Language :: Python :: 3.7
Classifier: Programming Language :: Python :: 3.8
Classifier: Programming Language :: Python :: Implementation :: CPython
Classifier: Programming Language :: Python :: Implementation :: PyPy
Requires-Dist: scikit-learn (>=0.19.1)
Requires-Dist: fuzzywuzzy (>=0.17.0)
Requires-Dist: openpyxl (>=2.6.2)
Requires-Dist: xpinyin (>=0.5.6)
Requires-Dist: gensim (>=3.7.1)
Requires-Dist: jieba (>=0.39)
Requires-Dist: xlrd (>=1.2.0)
Requires-Dist: tensorflow (>=1.8.0)
Requires-Dist: keras-bert (>=0.41.0)
Requires-Dist: Keras (>=2.2.0)
Requires-Dist: pandas (>=0.23.0)
Requires-Dist: h5py (>=2.7.1)
Requires-Dist: numpy (>=1.16.1)
Requires-Dist: pyemd (==0.5.1)
Requires-Dist: pathlib
Requires-Dist: translate
Requires-Dist: PyExecJS
Requires-Dist: stanfordcorenlp
